extraviadoscli/__init__.py
extraviadoscli/__main__.py
extraviadoscli/extraviadoscli.py
extraviadoscli/mpp.py
extraviadoscli/renders.py
extraviadoscli/webscrapers/__init__.py
extraviadoscli/webscrapers/base.py
extraviadoscli/webscrapers/utils.py
extraviadoscli/webscrapers/gro/__init__.py
extraviadoscli/webscrapers/gro/commons.py
extraviadoscli/webscrapers/gro/webscrapers.py
extraviadoscli/webscrapers/mor/__init__.py
extraviadoscli/webscrapers/mor/commons.py
extraviadoscli/webscrapers/mor/webscrapers.py
extraviadoscli-0.0.5.dist-info/LICENSE
extraviadoscli-0.0.5.dist-info/METADATA
extraviadoscli-0.0.5.dist-info/WHEEL
extraviadoscli-0.0.5.dist-info/entry_points.txt
extraviadoscli-0.0.5.dist-info/top_level.txt
extraviadoscli-0.0.5.dist-info/RECORD
