Metadata-Version: 2.1
Name: extraviadoscli
Version: 0.0.5
Summary: Use this web scraper to gather information about missing people from the official Prosecutor's Office websites of Mexico
Author-email: midir99 <midir99@proton.me>
License: GNU GENERAL PUBLIC LICENSE
Project-URL: Homepage, https://github.com/midir99/extraviadoscli
Keywords: extraviados,cli,mexico
Classifier: Development Status :: 3 - Alpha
Classifier: License :: OSI Approved :: GNU General Public License v3 (GPLv3)
Classifier: Programming Language :: Python
Classifier: Programming Language :: Python :: 3
Requires-Python: >=3.9
License-File: LICENSE
Requires-Dist: beautifulsoup4 (>=4.11.1)
Requires-Dist: requests (>=2.27.1)
Provides-Extra: dev
Requires-Dist: black ; extra == 'dev'
Requires-Dist: isort ; extra == 'dev'
Requires-Dist: pylint ; extra == 'dev'
Requires-Dist: pytest ; extra == 'dev'
